[{"VALUE":"aar","LEXIC":"Afar"},{"VALUE":"abk","LEXIC":"Abkhaze"},{"VALUE":"afr","LEXIC":"Afrikaans"},{"VALUE":"aka","LEXIC":"Akan"},{"VALUE":"amh","LEXIC":"Amharique"},{"VALUE":"arb","LEXIC":"Arabe"},{"VALUE":"arg","LEXIC":"Aragonais"},{"VALUE":"asm","LEXIC":"Assamais"},{"VALUE":"ava","LEXIC":"Avar"},{"VALUE":"ave","LEXIC":"Avestique"},{"VALUE":"aym","LEXIC":"Aymara"},{"VALUE":"aze","LEXIC":"Azéri"},{"VALUE":"bak","LEXIC":"Bachkir"},{"VALUE":"bam","LEXIC":"Bambara"},{"VALUE":"bel","LEXIC":"Biélorusse"},{"VALUE":"ben","LEXIC":"Bengali"},{"VALUE":"bih","LEXIC":"Bihari"},{"VALUE":"bis","LEXIC":"Bichelamar"},{"VALUE":"bod","LEXIC":"Tibétain"},{"VALUE":"bos","LEXIC":"Bosnien"},{"VALUE":"bre","LEXIC":"Breton"},{"VALUE":"bul","LEXIC":"Bulgare"},{"VALUE":"cat","LEXIC":"Catalan"},{"VALUE":"ces","LEXIC":"Tchèque"},{"VALUE":"cha","LEXIC":"Chamorro"},{"VALUE":"che","LEXIC":"Tchétchène"},{"VALUE":"chu","LEXIC":"Vieux-slave"},{"VALUE":"chv","LEXIC":"Tchouvache"},{"VALUE":"cor","LEXIC":"Cornique"},{"VALUE":"cos","LEXIC":"Corse"},{"VALUE":"cre","LEXIC":"Cri"},{"VALUE":"cym","LEXIC":"Gallois"},{"VALUE":"dan","LEXIC":"Danois"},{"VALUE":"deu","LEXIC":"Allemand"},{"VALUE":"div","LEXIC":"Maldivien"},{"VALUE":"dzo","LEXIC":"Dzongkha"},{"VALUE":"ell","LEXIC":"Grec moderne"},{"VALUE":"eng","LEXIC":"Anglais"},{"VALUE":"epo","LEXIC":"Espéranto"},{"VALUE":"est","LEXIC":"Estonien"},{"VALUE":"eus","LEXIC":"Basque"},{"VALUE":"ewe","LEXIC":"Ewe"},{"VALUE":"fao","LEXIC":"Féroïen"},{"VALUE":"fas","LEXIC":"Persan"},{"VALUE":"fij","LEXIC":"Fidjien"},{"VALUE":"fin","LEXIC":"Finnois"},{"VALUE":"fra","LEXIC":"Français"},{"VALUE":"fra","LEXIC":"Français ; langue fr"},{"VALUE":"fry","LEXIC":"Frison"},{"VALUE":"ful","LEXIC":"Peul"},{"VALUE":"gla","LEXIC":"Écossais"},{"VALUE":"gle","LEXIC":"Irlandais"},{"VALUE":"glg","LEXIC":"Galicien"},{"VALUE":"glv","LEXIC":"Mannois"},{"VALUE":"grn","LEXIC":"Guarani"},{"VALUE":"guj","LEXIC":"Gujarati"},{"VALUE":"hat","LEXIC":"Créole haïtien"},{"VALUE":"hau","LEXIC":"Haoussa"},{"VALUE":"hbs","LEXIC":"Serbo-croate"},{"VALUE":"heb","LEXIC":"Hébreu"},{"VALUE":"her","LEXIC":"Héréro"},{"VALUE":"hin","LEXIC":"Hindi"},{"VALUE":"hmo","LEXIC":"Hiri motu"},{"VALUE":"hrv","LEXIC":"Croate"},{"VALUE":"hun","LEXIC":"Hongrois"},{"VALUE":"hye","LEXIC":"Arménien"},{"VALUE":"ibo","LEXIC":"Igbo"},{"VALUE":"ido","LEXIC":"Ido"},{"VALUE":"iii","LEXIC":"Yi"},{"VALUE":"iku","LEXIC":"Inuktitut"},{"VALUE":"ile","LEXIC":"Occidental"},{"VALUE":"ina","LEXIC":"Interlingua"},{"VALUE":"ind","LEXIC":"Indonésien"},{"VALUE":"ipk","LEXIC":"Inupiak"},{"VALUE":"isl","LEXIC":"Islandais"},{"VALUE":"ita","LEXIC":"Italien"},{"VALUE":"jav","LEXIC":"Javanais"},{"VALUE":"jpn","LEXIC":"Japonais"},{"VALUE":"kal","LEXIC":"Groenlandais"},{"VALUE":"kan","LEXIC":"Kannada"},{"VALUE":"kas","LEXIC":"Cachemiri"},{"VALUE":"kat","LEXIC":"Géorgien"},{"VALUE":"kau","LEXIC":"Kanouri"},{"VALUE":"kaz","LEXIC":"Kazakh"},{"VALUE":"khm","LEXIC":"Khmer"},{"VALUE":"kik","LEXIC":"Kikuyu"},{"VALUE":"kin","LEXIC":"Kinyarwanda"},{"VALUE":"kir","LEXIC":"Kirghiz"},{"VALUE":"kom","LEXIC":"Komi"},{"VALUE":"kon","LEXIC":"Kikongo"},{"VALUE":"kor","LEXIC":"Coréen"},{"VALUE":"kua","LEXIC":"Kuanyama"},{"VALUE":"kur","LEXIC":"Kurde"},{"VALUE":"lao","LEXIC":"Lao"},{"VALUE":"lat","LEXIC":"Latin"},{"VALUE":"lav","LEXIC":"Letton"},{"VALUE":"lim","LEXIC":"Limbourgeois"},{"VALUE":"lin","LEXIC":"Lingala"},{"VALUE":"lit","LEXIC":"Lituanien"},{"VALUE":"ltz","LEXIC":"Luxembourgeois"},{"VALUE":"lub","LEXIC":"Luba-katanga"},{"VALUE":"lug","LEXIC":"Ganda"},{"VALUE":"mah","LEXIC":"Marshallais"},{"VALUE":"mal","LEXIC":"Malayalam"},{"VALUE":"mar","LEXIC":"Marathi"},{"VALUE":"mkd","LEXIC":"Macédonien"},{"VALUE":"mlg","LEXIC":"Malgache"},{"VALUE":"mlt","LEXIC":"Maltais"},{"VALUE":"mol","LEXIC":"Moldave"},{"VALUE":"mon","LEXIC":"Mongol"},{"VALUE":"mri","LEXIC":"Maori de Nouvelle-Zé"},{"VALUE":"msa","LEXIC":"Malais"},{"VALUE":"mya","LEXIC":"Birman"},{"VALUE":"nau","LEXIC":"Nauruan"},{"VALUE":"nav","LEXIC":"Navajo"},{"VALUE":"nbl","LEXIC":"Nrebele"},{"VALUE":"nde","LEXIC":"Sindebele"},{"VALUE":"ndo","LEXIC":"Ndonga"},{"VALUE":"nep","LEXIC":"Népalais"},{"VALUE":"nld","LEXIC":"Néerlandais"},{"VALUE":"nno","LEXIC":"Norvégien Nynorsk"},{"VALUE":"nob","LEXIC":"Norvégien Bokmål"},{"VALUE":"nor","LEXIC":"Norvégien"},{"VALUE":"nya","LEXIC":"Chichewa"},{"VALUE":"oci","LEXIC":"Occitan"},{"VALUE":"oji","LEXIC":"Ojibwé"},{"VALUE":"ori","LEXIC":"Oriya"},{"VALUE":"orm","LEXIC":"Oromo"},{"VALUE":"oss","LEXIC":"Ossète"},{"VALUE":"pan","LEXIC":"Pendjabi"},{"VALUE":"pli","LEXIC":"Pali"},{"VALUE":"pol","LEXIC":"Polonais"},{"VALUE":"por","LEXIC":"Portugais"},{"VALUE":"pus","LEXIC":"Pachto"},{"VALUE":"que","LEXIC":"Quechua"},{"VALUE":"roh","LEXIC":"Romanche"},{"VALUE":"ron","LEXIC":"Roumain"},{"VALUE":"run","LEXIC":"Kirundi"},{"VALUE":"rus","LEXIC":"Russe"},{"VALUE":"sag","LEXIC":"Sango"},{"VALUE":"san","LEXIC":"Sanskrit"},{"VALUE":"sin","LEXIC":"Cingalais"},{"VALUE":"slk","LEXIC":"Slovaque"},{"VALUE":"slv","LEXIC":"Slovène"},{"VALUE":"sme","LEXIC":"Same du Nord"},{"VALUE":"smo","LEXIC":"Samoan"},{"VALUE":"sna","LEXIC":"Shona"},{"VALUE":"snd","LEXIC":"Sindhi"},{"VALUE":"som","LEXIC":"Somali"},{"VALUE":"sot","LEXIC":"Sotho du Sud"},{"VALUE":"spa","LEXIC":"Espagnol"},{"VALUE":"sqi","LEXIC":"Albanais"},{"VALUE":"srd","LEXIC":"Sarde"},{"VALUE":"srp","LEXIC":"Serbe"},{"VALUE":"ssw","LEXIC":"Swati"},{"VALUE":"sun","LEXIC":"Soundanais"},{"VALUE":"swa","LEXIC":"Swahili"},{"VALUE":"swe","LEXIC":"Suédois"},{"VALUE":"tah","LEXIC":"Tahitien"},{"VALUE":"tam","LEXIC":"Tamoul"},{"VALUE":"tat","LEXIC":"Tatar"},{"VALUE":"tel","LEXIC":"Télougou"},{"VALUE":"tgk","LEXIC":"Tadjik"},{"VALUE":"tgl","LEXIC":"Tagalog"},{"VALUE":"tha","LEXIC":"Thaï"},{"VALUE":"tir","LEXIC":"Tigrigna"},{"VALUE":"ton","LEXIC":"Tongien"},{"VALUE":"tsn","LEXIC":"Tswana"},{"VALUE":"tso","LEXIC":"Tsonga"},{"VALUE":"tuk","LEXIC":"Turkmène"},{"VALUE":"tur","LEXIC":"Turc"},{"VALUE":"twi","LEXIC":"Twi"},{"VALUE":"uig","LEXIC":"Ouïghour"},{"VALUE":"ukr","LEXIC":"Ukrainien"},{"VALUE":"urd","LEXIC":"Ourdou"},{"VALUE":"uzb","LEXIC":"Ouzbek"},{"VALUE":"ven","LEXIC":"Venda"},{"VALUE":"vie","LEXIC":"Vietnamien"},{"VALUE":"vol","LEXIC":"Volapük"},{"VALUE":"wln","LEXIC":"Wallon"},{"VALUE":"wol","LEXIC":"Wolof"},{"VALUE":"xho","LEXIC":"Xhosa"},{"VALUE":"yid","LEXIC":"Yiddish"},{"VALUE":"yor","LEXIC":"Yoruba"},{"VALUE":"zgh","LEXIC":"Amazighe"},{"VALUE":"zha","LEXIC":"Zhuang"},{"VALUE":"zho","LEXIC":"Chinois"},{"VALUE":"zul","LEXIC":"Zoulou"}]
